suede/__init__.py
suede/bayesian_decoder_script.py
suede/synthetic_data_script.py
suede-0.1.1.dist-info/METADATA
suede-0.1.1.dist-info/WHEEL
suede-0.1.1.dist-info/top_level.txt
suede-0.1.1.dist-info/RECORD
