Metadata-Version: 2.1
Name: suede
Version: 0.1.1
Summary: Single-Unit Electrode DEcoding
Home-page: https://github.com/czbiohub/suede
Author: Gabby Shvartsman
Author-email: gabbyshvartsman@berkeley.edu
License: UNKNOWN
Platform: UNKNOWN
Requires-Python: >=3.6.0
